{
  "index": {
    "css": "css/derek.css",
    "theme_name": "derek"
  },
  "landing-page": {
    "css": "css/derek.css"
  },
  "solutions": {
    "css": "css/derek.css"
  },
  "solutions-usage": {
    "css": "css/derek.css"
  },
  "office365": {
    "css": "css/derek.css"
  },
  "homepage": {
    "css": "css/derek.css"
  },
  "section-overview": {
    "css": "css/derek.css"
  },
  "swatches": {
    "css": "css/derek.css"
  },
  "events": {
    "css": "css/derek.css"
  },
  "events-interior": {
    "css": "css/derek.css"
  },
  "stories": {
    "css": "css/derek.css"
  },
  "stories-interior": {
    "css": "css/derek.css"
  },
  "subpanels": {
    "css": "css/derek.css"
  }
}
